msfc_ccd/__init__.py
msfc_ccd/_cameras.py
msfc_ccd/_sensors.py
msfc_ccd/abc.py
msfc_ccd/fits.py
msfc_ccd/samples.py
msfc_ccd/_data/darks/ESIS1_00099.fit.gz
msfc_ccd/_data/darks/ESIS3_00099.fit.gz
msfc_ccd/_data/fe55/ESIS1_00002.fit
msfc_ccd/_data/fe55/ESIS3_05384.fit
msfc_ccd/_images/__init__.py
msfc_ccd/_images/_images.py
msfc_ccd/_images/_sensor_images.py
msfc_ccd/_images/_tap_images.py
msfc_ccd/_images/_vectors.py
msfc_ccd/_images/abc.py
msfc_ccd/_images/_tests/__init__.py
msfc_ccd/_images/_tests/test_images.py
msfc_ccd/_images/_tests/test_sensor_images.py
msfc_ccd/_images/_tests/test_tap_images.py
msfc_ccd/_images/_tests/test_vectors.py
msfc_ccd/_tests/__init__.py
msfc_ccd/_tests/test_cameras.py
msfc_ccd/_tests/test_fits.py
msfc_ccd/_tests/test_sensors.py
msfc_ccd-1.0.0.dist-info/METADATA
msfc_ccd-1.0.0.dist-info/WHEEL
msfc_ccd-1.0.0.dist-info/top_level.txt
msfc_ccd-1.0.0.dist-info/RECORD
