Metadata-Version: 2.4
Name: msfc-ccd
Version: 1.0.0
Summary: A Python library for characterizing and using the CCD cameras developed by Marshall Space Flight Center.
Author-email: "Roy T. Smart" <roytsmart@gmail.com>
Project-URL: Homepage, https://github.com/sun-data/msfc-ccd
Project-URL: Documentation, https://msfc-ccd.readthedocs.io/en/latest
Classifier: Programming Language :: Python :: 3
Requires-Python: >=3.11
Requires-Dist: astropy
Requires-Dist: named-arrays~=1.0
Requires-Dist: optika~=1.0
Provides-Extra: test
Requires-Dist: pytest; extra == "test"
Provides-Extra: doc
Requires-Dist: pytest; extra == "doc"
Requires-Dist: matplotlib; extra == "doc"
Requires-Dist: graphviz; extra == "doc"
Requires-Dist: sphinx-autodoc-typehints; extra == "doc"
Requires-Dist: sphinxcontrib-bibtex; extra == "doc"
Requires-Dist: pydata-sphinx-theme; extra == "doc"
Requires-Dist: ipykernel; extra == "doc"
Requires-Dist: jupyter-sphinx; extra == "doc"
Requires-Dist: nbsphinx; extra == "doc"
Requires-Dist: sphinx-codeautolink; extra == "doc"
Requires-Dist: sphinx-favicon; extra == "doc"
